TigerShark-0.3.4.data/scripts/convertPyX12.py
TigerShark-0.3.4.data/scripts/generate_all_parsers.py
tigershark/__init__.py
tigershark/util.py
tigershark/X12/__init__.py
tigershark/X12/file.py
tigershark/X12/parse.py
tigershark/X12/map/SQL.py
tigershark/X12/map/__init__.py
tigershark/X12/map/dj.py
tigershark/X12/map/source.py
tigershark/X12/message/__init__.py
tigershark/X12/message/sa.py
tigershark/extras/__init__.py
tigershark/extras/standardSegment.py
tigershark/facade/__init__.py
tigershark/facade/common.py
tigershark/facade/control.py
tigershark/facade/f270.py
tigershark/facade/f271.py
tigershark/facade/f27x.py
tigershark/facade/f835.py
tigershark/facade/f837.py
tigershark/facade/utils.py
tigershark/facade/enums/__init__.py
tigershark/facade/enums/common.py
tigershark/facade/enums/eligibility.py
tigershark/facade/enums/remittance.py
tigershark/parsers/M270_4010_X092_A1.py
tigershark/parsers/M270_5010_X279_A1.py
tigershark/parsers/M271_4010_X092_A1.py
tigershark/parsers/M271_5010_X279_A1.py
tigershark/parsers/M276_4010_X093_A1.py
tigershark/parsers/M277U_4010_X070.py
tigershark/parsers/M277_4010_X093_A1.py
tigershark/parsers/M278_4010_X094_27_A1.py
tigershark/parsers/M278_4010_X094_A1.py
tigershark/parsers/M820_4010_X061_A1.py
tigershark/parsers/M834_4010_X095_A1.py
tigershark/parsers/M835_4010_X091_A1.py
tigershark/parsers/M835_5010_X221_A1.py
tigershark/parsers/M837_4010_X096_A1.py
tigershark/parsers/M837_4010_X097_A1.py
tigershark/parsers/M837_4010_X098_A1.py
tigershark/parsers/M837_5010_X222_A1.py
tigershark/parsers/M837_5010_X223_A1.py
tigershark/parsers/M841_4010_XXXC.py
tigershark/parsers/__init__.py
tigershark/tools/__init__.py
tigershark/tools/convertPyX12.py
tigershark/tools/generate_all_parsers.py
tigershark/tools/rstFormat.py
tigershark/tools/surveyPyX12.py
tigershark/tools/utils.py
TigerShark-0.3.4.dist-info/AUTHORS
TigerShark-0.3.4.dist-info/LICENSE
TigerShark-0.3.4.dist-info/METADATA
TigerShark-0.3.4.dist-info/WHEEL
TigerShark-0.3.4.dist-info/top_level.txt
TigerShark-0.3.4.dist-info/RECORD
