Metadata-Version: 2.1
Name: TigerShark
Version: 0.3.4
Summary: TigerShark: An X12 file parser.
Home-page: UNKNOWN
Author: Steven Buss & Steven Lott & Dave Peticolas
Author-email: dave.peticolas@gmail.com
License: UNKNOWN
Download-URL: https://github.com/jdavisp3/TigerShark/tarball/v0.3.4
Platform: UNKNOWN
Classifier: Development Status :: 3 - Alpha
Classifier: Intended Audience :: Developers
Classifier: Intended Audience :: Healthcare Industry
Classifier: License :: OSI Approved :: BSD License
Classifier: Operating System :: OS Independent
Classifier: Topic :: Text Processing
Classifier: Programming Language :: Python :: 2
Classifier: Programming Language :: Python :: 2.7
Classifier: Programming Language :: Python :: 3
Classifier: Programming Language :: Python :: 3.5
License-File: LICENSE
License-File: AUTHORS
